solr_helper/__init__.py
solr_helper/config.py
solr_helper/main.py
solr_helper/solr_client.py
solr_helper/web/__init__.py
solr_helper/web/app.py
solr_helper/web/routes/__init__.py
solr_helper/web/routes/api.py
solr_helper/web/routes/connection.py
solr_helper/web/routes/record.py
solr_helper/web/routes/search.py
solr_helper/web/templates/_base.html
solr_helper/web/templates/_edit_form.html
solr_helper/web/templates/_header.html
solr_helper/web/templates/_record_row.html
solr_helper/web/templates/_toast.html
solr_helper/web/templates/connections.html
solr_helper/web/templates/index.html
solr_helper/web/templates/record.html
solr_helper/web/templates/search_results.html
solr_helper/web/templates/use_connection.html
solr_helper/web/utils/__init__.py
solr_helper/web/utils/auth.py
solr_helper/web/utils/helpers.py
solr_helper-1.5.0.dist-info/licenses/LICENSE
solr_helper-1.5.0.dist-info/METADATA
solr_helper-1.5.0.dist-info/WHEEL
solr_helper-1.5.0.dist-info/entry_points.txt
solr_helper-1.5.0.dist-info/top_level.txt
solr_helper-1.5.0.dist-info/RECORD
