Metadata-Version: 2.4
Name: solr-helper
Version: 1.5.0
Summary: Tool zum Anzeigen und Bearbeiten von Solr-Dokumenten.
Author-email: Thomas Baer <thomas.baer@slub-dresden.de>
License: MIT License
Project-URL: Homepage, https://github.com/thomsbe/SolrHelper
Project-URL: Repository, https://github.com/thomsbe/SolrHelper
Project-URL: Bug Tracker, https://github.com/thomsbe/SolrHelper/issues
Keywords: solr,helper,flask,htmx,search,admin
Classifier: Development Status :: 5 - Production/Stable
Classifier: Framework :: Flask
Classifier: Intended Audience :: Developers
Classifier: Intended Audience :: System Administrators
Classifier: Operating System :: OS Independent
Classifier: Programming Language :: Python :: 3
Classifier: Programming Language :: Python :: 3.12
Classifier: Topic :: Internet :: WWW/HTTP :: WSGI :: Application
Classifier: Topic :: Software Development :: Libraries :: Python Modules
Requires-Python: <3.13,>=3.12
License-File: LICENSE
Requires-Dist: flask>=3.1.1
Requires-Dist: click>=8.2.1
Requires-Dist: loguru>=0.7.3
Requires-Dist: pysolr>=3.10.0
Requires-Dist: requests>=2.32.4
Requires-Dist: toml>=0.10.2
Dynamic: license-file
